lektor_webpack_support.py
lektor_webpack_support-0.6.0.dist-info/LICENSE
lektor_webpack_support-0.6.0.dist-info/METADATA
lektor_webpack_support-0.6.0.dist-info/WHEEL
lektor_webpack_support-0.6.0.dist-info/entry_points.txt
lektor_webpack_support-0.6.0.dist-info/top_level.txt
lektor_webpack_support-0.6.0.dist-info/RECORD
