Metadata-Version: 2.1
Name: lektor-webpack-support
Version: 0.6.0
Summary: Super simple Lektor plugin that runs a webpack watcher
Home-page: https://github.com/lektor/lektor-webpack-support
Author: Armin Ronacher
Author-email: armin.ronacher@active-4.com
License: BSD
Keywords: Lektor,plugin,static-site,node,webpack,yarn,scss
Platform: UNKNOWN
Classifier: Environment :: Plugins
Classifier: Environment :: Web Environment
Classifier: Framework :: Lektor
Classifier: Intended Audience :: Developers
Classifier: License :: OSI Approved :: BSD License
License-File: LICENSE
